Workbook

Sheet Cover page
A1: Project Title
A2: Comparable Company Valuation
A4: Target Company
A5: Volkswagen AG
A7: Prepared by
A8: Muddangula Charitha
A10: Date | B10: 46087
A12: Valuation Method
A13: Comparable Company Analysis
A15: Currency:
A16: EUR (MILLIONS)
A18: LOGO
A19: Data Source:
A20: Company Annual Reports
A21: Investor Presentations
A22: Yahoo Finance
A25: LOGO:

Sheet Data source
A1: Data Sources
A3: Sources:
A5: Company Annual Reports
A6: Investor Presentations
A7: Yahoo Finance

Sheet Investment summary
A1: Investment Summary
A3: Item | B3: Value
A4: Target Company | B4: Volkswagen AG
A5: Industry | B5: Global Automotive
A6: Valuation Method | B6: Trading Comparables
A7: Current Price | B7: 120
A8: Implied Fair Value | B8: 200-230
A9: Upside | B9: 75–100%
A10: Recommendation | B10: BUY
A13: Volkswagen trades at a discount to peer median EV/EBITDA, indicating potential undervaluation.

Sheet Company overview
A1: Company Overview
A3: Item | B3: Value
B4: 1937
A5: Headquarters | B5: Wolfsburg
A6: Employees | B6: ~670,000
A7: Brands | B7: VW, Audi, Porsche, Skoda
A8: Business Segments | B8: Passenger Cars, Commercial Vehicles
A11: Volkswagen AG
A12: Metric | B12: Value
A13: Revenue CAGR | B13: 0.0907
A14: EBITDA Margin | B14: 0.1466
A15: EBIT Margin | B15: 0.0587
A17: BMW
A18: Metric | B18: VALUE
A19: Revenue CAGR | B19: 1.6839
A20: EBITDA Margin | B20: 0.1418
A21: EBIT Margin | B21: 0.0811
A23: Mercedes
A24: Metric | B24: VALUE
A25: Revenue CAGR | B25: 0.3981
A26: EBITDA Margin | B26: 0.1477
A27: EBIT Margin | B27: 0.1012
A29: FORD
A30: Metric | B30: VALUE
A31: Revenue CAGR | B31: 0.971
A32: EBITDA Margin | B32: 0.0194
A33: EBIT Margin | B33: -0.0561

Sheet Comparable company selection
A1: Comparable Company Selection
A3: Company | B3: Country | C3: Reason for Inclusion
A4: BMW AG | B4: Germany | C4: Premium segment
A5: Mercedes-Benz Group AG | B5: Germany | C5: Comparable margins
A6: Ford Motor Company | B6: USA | C6: Mass market OEM
A9: Peers selected based on
A11: Global scale
A12: Similar revenue range
A13: Comparable operating margins
A14: Exposure to passenger vehicle segment
A16: “Peers selected include Toyota, BMW, Mercedes-Benz, and Ford based on industry similarity, scale, and operating profile.”

Sheet Financial performance
A1: Historical Financial Performance
A2: Volkswagen AG
A3: Year | B3: Revenue (€ million) | C3: EBITDA (€ million) | D3: EBIT (€ million) | E3: Net Income (€ million)
A4: 2021 | B4: 250200 | C4: 42000 | D4: 19275 | E4: 15428
A5: 2022 | B5: 279232 | C5: 38300 | D5: 22124 | E5: 15836
A6: 2023 | B6: 322284 | C6: 44600 | D6: 22528 | E6: 17861
A7: 2024 | B7: 324656 | C7: 47600 | D7: 19060 | E7: 12394
A10: Metric | B10: Value
A11: Revenue CAGR | B11: =(B7/B4)^(1/3)-1 -> 0.090716901
A12: EBITDA Margin | B12: =C7/B7 -> 0.14661673
A13: EBIT Margin | B13: =D7/B7 -> 0.058708294
A16: BMW
A17: Year | B17: Revenue (€ million) | C17: EBITDA (€ million) | D17: EBIT (€ million) | E17: Net Income (€ million) | H17: Metric | I17: VALUE
A18: 2021 | B18: 111239 | C18: 22791 | D18: 16296 | E18: 12382 | H18: Revenue CAGR | I18: =(B21/B18)^(1+3)-1 -> 1.6839082
A19: 2022 | B19: 142610 | C19: 32305 | D19: 23739 | E19: 17941 | H19: EBITDA Margin | I19: =C21/B21 -> 0.14183172
A20: 2023 | B20: 155498 | C20: 26726 | D20: 17752 | E20: 11290 | H20: EBIT Margin | I20: =D21/B21 -> 0.081078803
A21: 2024 | B21: 142380 | C21: 20194 | D21: 11544 | E21: 7290
A23: Mercedes
A24: Year | B24: Revenue (€ million) | C24: EBITDA (€ million) | D24: EBIT (€ million) | E24: Net Income (€ million) | H24: Metric | I24: VALUE
A25: 2021 | B25: 133893 | C25: 23220 | D25: 16240 | E25: 10660 | H25: Revenue CAGR | I25: =(B28/B25)^(1+3)-1 -> 0.39811348
A26: 2022 | B26: 150017 | C26: 27252 | D26: 20731 | E26: 14501 | H26: EBITDA Margin | I26: =C28/B28 -> 0.14770526
A27: 2023 | B27: 152390 | C27: 27438 | D27: 20775 | E27: 14261 | H27: EBIT Margin | I27: =D28/B28 -> 0.10119236
A28: 2024 | B28: 145594 | C28: 21505 | D28: 14733 | E28: 10207
A30: FORD
A31: Year | B31: Revenue ($ million) | C31: EBITDA ($ million) | D31: EBIT ($ million) | E31: Net Income ($ million) | H31: Metric | I31: VALUE
A32: 2021 | B32: 158057 | C32: 4759 | D32: -1734 | E32: -1981 | H32: Revenue CAGR | I32: =(B35/B32)^(1+3)-1 -> 0.97056187
A33: 2022 | B33: 176191 | C33: 11808 | D33: 5285 | E33: 4347 | H33: EBITDA Margin | I33: =C35/B35 -> 0.019426808
A34: 2023 | B34: 184992 | C34: 14236 | D34: 8369 | E34: 5879 | H34: EBIT Margin | I34: =D35/B35 -> -0.056053656
A35: 2024 | B35: 187267 | C35: 3638 | D35: -10497 | E35: -8182

Sheet Market Data
A1: Market Data
A3: Company | B3: Share Price | C3: Shares | D3: Market Cap
A4: Volkswagen | B4: 92.8 | C4: 509.12 | D4: =B4*C4 -> 47246.336
A5: BMW | B5: 81.42 | C5: 556.08 | D5: =B5*C5 -> 45276.034
A6: Mercedes | B6: 55.65 | C6: 884.84 | D6: =B6*C6 -> 49241.346
A7: Ford | B7: 64.97 | C7: 3.92 | D7: =B7*C7 -> 254.6824

Sheet Capital structure
A1: Capital Structure | B1: (IN MILLONS)
A3: Company | B3: Debt | C3: Cash | D3: Net Debt
A4: Volkswagen AG | B4: 196520 | C4: 47472 | D4: =B4-C4 -> 149048
A5: BMW | B5: 85504 | C5: 21840 | D5: =B5-C5 -> 63664
A6: Mercedes-Benz Group | B6: 93042 | C6: 16744 | D6: =B6-C6 -> 76298
A7: Ford Motor Company | B7: 160862 | C7: 25275 | D7: =B7-C7 -> 135587

Sheet EV calculation
A1: Enterprise Value Calculation
A3: Company | B3: Market Cap | C3: Net Debt | D3: Enterprise Value
A4: Volkswagen | B4: ='Market Data'!D4 -> 47246.336 | C4: ='Capital structure'!D4 -> 149048 | D4: =B4+C4 -> 196294.34
A5: BMW | B5: ='Market Data'!D5 -> 45276.034 | C5: ='Capital structure'!D5 -> 63664 | D5: =B5+C5 -> 108940.03
A6: Mercedes | B6: ='Market Data'!D6 -> 49241.346 | C6: ='Capital structure'!D6 -> 76298 | D6: =B6+C6 -> 125539.35
A7: Ford | B7: ='Market Data'!D7 -> 254.6824 | C7: ='Capital structure'!D7 -> 135587 | D7: =B7+C7 -> 135841.68

Sheet Peer mutliples
A1: Peer Multiples Statistics
A3: Metric | B3: EV/Revenue | C3: EV/EBITDA | D3: EV/EBIT
A4: Min | B4: =MIN('Trading mutliples'!B5:B7) -> 0.72539039 | C4: =MIN('Trading mutliples'!C5:C7) -> 0.72539039 | D4: =MIN('Trading mutliples'!D5:D7) -> 0.72539039
A5: Max | B5: =MAX('Trading mutliples'!B5:B7) -> 0.86225632 | C5: =MAX('Trading mutliples'!C5:C7) -> 5.8376817 | D5: =MAX('Trading mutliples'!D5:D7) -> 10.874857
A6: Mean | B6: =GEOMEAN('Trading mutliples'!B5:B7) -> 0.78219596 | C6: =GEOMEAN('Trading mutliples'!C5:C7) -> 2.8374341 | D6: =GEOMEAN('Trading mutliples'!D5:D7) -> 4.0659435
A7: Median | B7: =MEDIAN('Trading mutliples'!B5:B7) -> 0.76513579 | C7: =MEDIAN('Trading mutliples'!C5:C7) -> 5.3946733 | D7: =MEDIAN('Trading mutliples'!D5:D7) -> 8.5209629

Sheet Trading mutliples
A1: Trading Multiples
A3: Company | B3: EV/Revenue | C3: EV/EBITDA | D3: EV/EBIT
A4: Volkswagen | B4: ='EV calculation'!D4/'Financial performance'!B7 -> 0.60462254 | C4: ='EV calculation'!D4/'Financial performance'!C7 -> 4.1238306 | D4: ='EV calculation'!D4/'Financial performance'!D7 -> 10.298758
A5: BMW | B5: ='EV calculation'!D5/'Financial performance'!B21 -> 0.76513579 | C5: ='EV calculation'!D5/'Financial performance'!C21 -> 5.3946733 | D5: ='EV calculation'!D6/'Financial performance'!D21 -> 10.874857
A6: Mercedes | B6: ='EV calculation'!D6/'Financial performance'!B28 -> 0.86225632 | C6: ='EV calculation'!D6/'Financial performance'!C28 -> 5.8376817 | D6: ='EV calculation'!D6/'Financial performance'!D28 -> 8.5209629
A7: Ford | B7: ='EV calculation'!D7/'Financial performance'!B35 -> 0.72539039 | C7: ='EV calculation'!D7/'Financial performance'!B35 -> 0.72539039 | D7: ='EV calculation'!D7/'Financial performance'!B35 -> 0.72539039

Sheet MUTLIPLES CAHRT
A1: EV/EBITDA MUTLIPLES
A3: Company | B3: EV/EBITDA
A4: Volkswagen | B4: 4.1
A5: Mercedes | B5: 5.8
A6: BMW | B6: 6
A7: Ford | B7: 6.8
A25: “Volkswagen AG trades at the lowest EV/EBITDA multiple among peers, indicating potential undervaluation.”

Sheet Equity value
A1: Equity Value Bridge
A3: Item | B3: Value
A4: Enterprise Value | B4: 256786
A5: Net Debt | B5: 149048
A6: Equity Value | B6: 107738
A7: Shares | B7: 509.12
A8: Implied Share Price | B8: 211.6

Sheet Implied valuation
A1: Implied Valuation
A3: Method | B3: Multiple | C3: Metric | D3: Implied EV
A4: EV/Revenue | B4: 0.73 | C4: ='Financial performance'!B7 -> 324656 | D4: =B4*C4 -> 236998.88
A5: EV/EBITDA | B5: ='Peer mutliples'!C7 -> 5.3946733 | C5: ='Financial performance'!C7 -> 47600 | D5: =B5*C5 -> 256786.45
A6: EV/EBIT | B6: ='Peer mutliples'!D7 -> 8.5209629 | C6: ='Financial performance'!D7 -> 19060 | D6: =B6*C6 -> 162409.55

Sheet Valuation Range
A1: Valuation Range
A3: Method | B3: Price
A4: EV/Revenue | B4: =C4/'Equity value'!B7 -> 172.75079 | C4: ='Implied valuation'!D4-'EV calculation'!C4 -> 87950.88
A5: EV/EBITDA | B5: =C5/'Equity value'!B7 -> 211.61701 | C5: ='Implied valuation'!D5-'EV calculation'!C4 -> 107738.45
A6: EV/EBIT | B6: =C6/'Equity value'!B7 -> 26.244407 | C6: ='Implied valuation'!D6-'EV calculation'!C4 -> 13361.552

Sheet Sensitivity Analysis
A1: Sensitivity Analysis
A3: EBITDA Multiple | B3: 5x | C3: 6x | D3: 7x
A4: Share Price (€) | B4: 174.7 | C4: 268.2 | D4: 361.7

Sheet INVESTMENT THESIS
A1: INVESTMENT THESIS
A4: Volkswagen trades at ~4.1x EV/EBITDA, below peer median of ~5.5x.
A5: This suggests a ~25% valuation discount.
A6: Despite concerns around EV transition and capital intensity, strong brands such as Audi and Porsche support long-term profitability.
A7: Based on peer multiples, fair value is estimated at €200–€220, implying upside potential.
A9: Recommendation: BUY
A12: Risks
A14: • EV Transition Risk
A15: Volkswagen faces high capital expenditure requirements for electric vehicle expansion, which may pressure short-term profitability and margins.
A17: • Margin Pressure Risk
A18: Compared to premium peers, Volkswagen operates at relatively lower margins due to its mass-market positioning and cost structure.
A20: • Cyclical Demand Risk
... A30: The valuation is dependent on peer multiples, which may fluctuate based on market conditions, potentially affecting the implied fair value.
